AUTHORS.rst
CHANGELOG.rst
LICENSE
MANIFEST.in
README.rst
setup.py
django_ultracache_twisted.egg-info/PKG-INFO
django_ultracache_twisted.egg-info/SOURCES.txt
django_ultracache_twisted.egg-info/dependency_links.txt
django_ultracache_twisted.egg-info/requires.txt
django_ultracache_twisted.egg-info/top_level.txt
example/config.yaml
example/dev-purge.sh
example/requirements.txt
purge/__init__.py
purge/__init__.pyc
twisted/plugins/dropin.cache
twisted/plugins/purge_plugin.py
twisted/plugins/purge_plugin.pyc