Metadata-Version: 1.1
Name: django-ultracache-twisted
Version: 0.0.3
Summary: Companion app to django-ultracache that enables proxy invalidation
Home-page: http://github.com/praekelt/django-ultracache-twisted
Author: Praekelt Consulting
Author-email: dev@praekelt.com
License: BSD
Platform: UNKNOWN
Classifier: Development Status :: 4 - Beta
Classifier: Intended Audience :: Developers
Classifier: License :: OSI Approved :: BSD License
Classifier: Operating System :: POSIX
Classifier: Programming Language :: Python
Classifier: Topic :: Software Development :: Libraries :: Python Modules
Classifier: Topic :: System :: Networking
